TM1py/__init__.py
TM1py/Exceptions/Exceptions.py
TM1py/Exceptions/__init__.py
TM1py/Objects/Annotation.py
TM1py/Objects/Application.py
TM1py/Objects/Axis.py
TM1py/Objects/Chore.py
TM1py/Objects/ChoreFrequency.py
TM1py/Objects/ChoreStartTime.py
TM1py/Objects/ChoreTask.py
TM1py/Objects/Cube.py
TM1py/Objects/Dimension.py
TM1py/Objects/Element.py
TM1py/Objects/ElementAttribute.py
TM1py/Objects/Git.py
TM1py/Objects/GitCommit.py
TM1py/Objects/GitPlan.py
TM1py/Objects/GitRemote.py
TM1py/Objects/Hierarchy.py
TM1py/Objects/MDXView.py
TM1py/Objects/NativeView.py
TM1py/Objects/Process.py
TM1py/Objects/Rules.py
TM1py/Objects/Sandbox.py
TM1py/Objects/Server.py
TM1py/Objects/Subset.py
TM1py/Objects/TM1Object.py
TM1py/Objects/User.py
TM1py/Objects/View.py
TM1py/Objects/__init__.py
TM1py/Services/AnnotationService.py
TM1py/Services/ApplicationService.py
TM1py/Services/CellService.py
TM1py/Services/ChoreService.py
TM1py/Services/CubeService.py
TM1py/Services/DimensionService.py
TM1py/Services/ElementService.py
TM1py/Services/GitService.py
TM1py/Services/HierarchyService.py
TM1py/Services/MonitoringService.py
TM1py/Services/ObjectService.py
TM1py/Services/PowerBiService.py
TM1py/Services/ProcessService.py
TM1py/Services/RestService.py
TM1py/Services/SandboxService.py
TM1py/Services/SecurityService.py
TM1py/Services/ServerService.py
TM1py/Services/SubsetService.py
TM1py/Services/TM1Service.py
TM1py/Services/ViewService.py
TM1py/Services/__init__.py
TM1py/Utils/MDXUtils.py
TM1py/Utils/Utils.py
TM1py/Utils/__init__.py
TM1py-1.8.0.dist-info/LICENSE
TM1py-1.8.0.dist-info/METADATA
TM1py-1.8.0.dist-info/WHEEL
TM1py-1.8.0.dist-info/top_level.txt
TM1py-1.8.0.dist-info/RECORD
