Metadata-Version: 2.1
Name: TM1py
Version: 1.8.0
Summary: A python module for TM1.
Home-page: https://github.com/cubewise-code/tm1py
Author: Marius Wirtz
Author-email: MWirtz@cubewise.com
License: MIT
Download-URL: https://github.com/Cubewise-code/TM1py/tarball/1.8.0
Keywords: TM1,IBM Cognos TM1,Planning Analytics,PA,Cognos
Platform: UNKNOWN
Classifier: Intended Audience :: Developers
Classifier: License :: OSI Approved :: MIT License
Classifier: Programming Language :: Python
Classifier: Programming Language :: Python :: 3.6
Classifier: Programming Language :: Python :: 3.7
Classifier: Programming Language :: Python :: 3.8
Classifier: Programming Language :: Python :: 3.9
Classifier: Natural Language :: English
Requires-Python: >=3.6
License-File: LICENSE
Requires-Dist: requests
Requires-Dist: pytz
Requires-Dist: mdxpy
Requires-Dist: requests-negotiate-sspi ; platform_system == "Windows"
Provides-Extra: pandas
Requires-Dist: pandas ; extra == 'pandas'
